[
  {
    "full_name": "HeroicHitesh/mern-blog",
    "stargazers_count": 1,
    "open_issues_count": 0,
    "forks_count": 0
  },
  {
    "full_name": "daumann/ECMAScript-new-features-list",
    "stargazers_count": 3482,
    "open_issues_count": 4,
    "forks_count": 532
  },
  {
    "full_name": "kamranahmedse/developer-roadmap",
    "stargazers_count": 297322,
    "open_issues_count": 48,
    "forks_count": 39148
  },
  {
    "full_name": "adam-p/markdown-here",
    "stargazers_count": 59638,
    "open_issues_count": 325,
    "forks_count": 11260
  },
  {
    "full_name": "cobiwave/simplefolio",
    "stargazers_count": 13459,
    "open_issues_count": 77,
    "forks_count": 5738
  }
]